{
  "common": {
    "login": "O'mölon",
    "home": "Dahoam",
    "results": "Ergebnisse",
    "sports": "Sportoatn",
    "medalTable": "Medaillenspiagl",
    "countries": "Lända",
    "athletes": "Athletn",
    "noMedalsYet": "Noch keine Medaljn",
    "noResults": "Keine Ergebnisse gfundn",
    "tryDifferentSearch": "Probier an andern Suachbegriff",
    "welcomeBack": "Servus wieda do",
    "loginDescription": "Meld di o, damit'st zum Kampfrichda-Dashboard kimmst",
    "email": "E-Mail",
    "password": "Passwoat",
    "forgotPassword": "Passwoat vagessn",
    "loginAction": "O'mölon",
    "forgotPasswordTitle": "Passwoat vagessn",
    "emailSentTitle": "E-Mail is raus",
    "enterEmailForReset": "Gib dei E-Mail ei, damit dei Passwoat wieda herrichtn kannst",
    "resetLinkSent": "A Link zum Passwoat wieda herrichtn is an dei E-Mail gschickt woarn",
    "backToLogin": "Zruck zum O'mölon",
    "sending": "Wird gschickt...",
    "authenticating": "Wird o'gmölt...",
    "language": "Sproch",
    "selectLanguage": "Sproch aussuacha",
    "lastUpdate": "Letztes Update",
    "disclaimer": "Alle Ergebnisse san offizielle Daten vom Internationalen Olympischen Komitee (IOC).",
    "privacy": "Datenschutz",
    "imprint": "Impressum",
    "accessibility": "Barrierefreiheit",
    "copyright": "© 2026 Olympia 2026 Results Portal. Alle Rechte voabehalten.",
    "events": "Wettbewerbe",
    "nations": "Nationan",
    "medals": "Medaljn"
  },
  "hero": {
    "headline": "Ergebnisse vo de Olympischn Spüle 2026",
    "subtitle": "Alle Wettkämpf. Alle Medaljn. Live.",
    "searchPlaceholder": "Athlet, Land, Disziplin oder Event suachn...",
    "cta": "Zu de Ergebnisse"
  },
  "highlights": {
    "title": "Highlights",
    "subtitle": "Die neuesten Medaljnmomente",
    "viewAll": "Alle Highlights",
    "watchVideo": "Video o'schaun"
  },
  "liveResults": {
    "title": "Live-Ergebnisse",
    "subtitle": "Biathlon - 10km Sprint Herren",
    "rank": "Plotz",
    "athlete": "Athlet/Team",
    "country": "Land",
    "result": "Ergebnis",
    "medal": "Medalj",
    "viewAll": "Alle Ergebnisse o'zoagn",
    "status": {
      "live": "Live",
      "final": "Final",
      "corrected": "Korrigiert"
    }
  },
  "medalTable": {
    "title": "Medaillenspiagl",
    "subtitle": "Top 10 Nationan",
    "rank": "Rang",
    "country": "Land",
    "gold": "Gold",
    "silver": "Sülba",
    "bronze": "Bronze",
    "total": "Gsamt",
    "viewAll": "Alle o'zoagn"
  },
  "medalTableDetail": {
    "title": "Medaillenspiagl",
    "subtitle": "Vollständige Ranglistn vo olle teilnehmenden Nationan",
    "allNations": "Alle Nationan",
    "searchPlaceholder": "Land suachn...",
    "compare": "Vagleichn",
    "showing": "Zoag",
    "to": "bis",
    "of": "vo",
    "nations": "Nationan"
  },
  "sports": {
    "title": "Sportoatn",
    "subtitle": "Suach da a Sportoat aus, damit'st de Ergebnisse siachst",
    "items": {
      "biathlon": "Biathlon",
      "iceHockey": "Eishockey",
      "crossCountrySkiing": "Skilanglauf",
      "skiJumping": "Skispringan",
      "bobsled": "Bobsport",
      "figureSkating": "Eiskunstlauf",
      "curling": "Curling",
      "luge": "Rennrodeln",
      "nordicCombined": "Nordische Kombination",
      "shortTrack": "Shorttrack",
      "skeleton": "Skeleton",
      "alpineSkiing": "Alpina Skifoahrt",
      "freestyle": "Freestyle-Skiing",
      "snowboard": "Snowboard",
      "speedSkating": "Eisschnelllauf"
    },
    "overview": {
      "title": "Sportoatn",
      "subtitle": "Alle 15 olympischn Wintasportoatn",
      "searchPlaceholder": "Sportoat suachn...",
      "totalSports": "Sportoatn",
      "totalEvents": "Wettbewerbe",
      "totalMedals": "Medaljn",
      "totalNations": "Nationan",
      "events": "Wettbewerbe",
      "medals": "Medaljn"
    },
    "detail": {
      "breadcrumb": "Sportoatn",
      "eventsAndResults": "Wettkampfplan & Ergebnisse",
      "disciplines": "Disziplinen",
      "disciplinesCount": "Disziplinen",
      "medalsCount": "Medaljn",
      "description": {
        "biathlon": "Kombination aus Skilanglauf und Schiaßn",
        "bobsled": "Gschwindigkeit auf Eis",
        "crossCountrySkiing": "Ausdaua im Schnee",
        "curling": "Präzision aufm Eis",
        "figureSkating": "Kunst und Athletik",
        "iceHockey": "Schnelligkeit und Teamwoark",
        "luge": "Rasant auf Kufen",
        "nordicCombined": "Springan und Langlauf",
        "shortTrack": "Gschwindigkeit auf kuaza Bahn",
        "skeleton": "Kopfüba ins Ziel",
        "alpineSkiing": "Gschwindigkeit am Berg",
        "skiJumping": "Fliagn durch de Luft",
        "freestyle": "Tricks und Stunts",
        "snowboard": "Style aufm Board",
        "speedSkating": "Tempo auf da langen Bahn"
      },
      "eventInfo": {
        "date": "Datum",
        "time": "Zeit",
        "location": "Ort",
        "status": {
          "live": "Live",
          "final": "Final",
          "draft": "Entwurf",
          "scheduled": "Geplant"
        },
        "viewResults": "Ergebnisse"
      }
    }
  },
  "nations": {
    "title": "Lända",
    "subtitle": "Olympische Wintaspüle Milano-Cortina 2026",
    "breadcrumb": "Lända",
    "totalMedals": "Gsamt",
    "allResults": "Alle Ergebnisse",
    "searchPlaceholder": "Suachn...",
    "filters": {
      "allSports": "Alle Sportoatn",
      "all": "Alle",
      "date": "Datum"
    },
    "table": {
      "sport": "Sportoat / Disziplin",
      "athlete": "Athlet",
      "result": "Ergebnis",
      "medal": "Medalj",
      "status": "Status"
    },
    "topAthletes": "Top-Athletn",
    "showAllAthletes": "Alle Athletn o'zoagn",
    "medalTimeline": "Medaljn-Timeline",
    "overview": {
      "title": "Alle teilnehmenden Nationan",
      "subtitle": "Lända bei de Olympischn Wintaspüle 2026",
      "searchPlaceholder": "Noch Land oder Code suachn...",
      "sortBy": "Sortian noch",
      "sortByName": "Nama",
      "sortByMedals": "Medaljn",
      "filterByMedals": "Medaljn filtan",
      "withMedals": "Mit Medaljn",
      "allCountries": "Alle Lända",
      "participatingNations": "Teilnehmende Nationan",
      "viewDetails": "Details o'zoagn"
    }
  },
  "resultsPage": {
    "title": "Ergebnisse",
    "subtitle": "Alle veröffentlichten Wettkampfergebnisse",
    "breadcrumb": "Ergebnisse",
    "searchPlaceholder": "Athlet oder Event suachn...",
    "filterSport": "Sportoat",
    "filterCountry": "Land",
    "filterDate": "Datum",
    "allSports": "Alle Sportoatn",
    "allCountries": "Alle Lända",
    "noResults": "Keine Ergebnisse gfundn",
    "noResultsHint": "Probier de Filter o'zupassn",
    "rank": "Plotz",
    "medal": "Medalj",
    "athlete": "Athlet",
    "country": "Land",
    "result": "Ergebnis",
    "event": "Wettbewerb",
    "lastModified": "Zuletzt geändert",
    "page": "Seite",
    "of": "vo",
    "viewDetail": "Details o'zoagn"
  },
  "resultDetail": {
    "title": "Ergebnis-Detail",
    "breadcrumb": "Ergebnis",
    "eventInfo": "Wettbewerb-Informationen",
    "sport": "Sportoat",
    "date": "Datum",
    "location": "Ort",
    "version": "Version",
    "relatedResults": "Ergebnisse vo dem Wettbewerb"
  },
  "athleteProfile": {
    "title": "Athletnprofil",
    "breadcrumb": "Athlet",
    "age": "Oida",
    "country": "Land",
    "disciplines": "Disziplinen",
    "results": "Ergebnisse",
    "noResults": "Noch keine veröffentlichten Ergebnisse"
  },
  "countryMedals": {
    "title": "Medaljn-Details",
    "breadcrumb": "Land",
    "medals": "Medaljn",
    "results": "Medaljn-Ergebnisse",
    "gold": "Gold",
    "silver": "Sülba",
    "bronze": "Bronze",
    "total": "Gsamt"
  },
  "judge": {
    "dashboard": {
      "title": "Kampfrichda-Dashboard",
      "subtitle": "Übersicht vo deine Ergebnisse",
      "drafts": "Entwürf",
      "pendingReview": "Warten auf Prüfung",
      "published": "Veröffentlicht",
      "protests": "Proteste",
      "invalid": "Ungültig",
      "newResult": "Neues Ergebnis",
      "myDrafts": "Meine Entwürf",
      "reviewQueue": "Prüf-Warteschlange"
    },
    "results": {
      "title": "Meine Ergebnisse",
      "subtitle": "Alle deine Ergebnisse vawaltn",
      "all": "Alle",
      "filterDraft": "Entwurf",
      "filterPending": "Wartend",
      "filterPublished": "Veröffentlicht",
      "filterInvalid": "Ungültig",
      "event": "Wettbewerb",
      "athlete": "Athlet",
      "sport": "Sportoat",
      "value": "Wert",
      "status": "Status",
      "version": "Version",
      "lastModified": "Zuletzt geändert",
      "actions": "Aktionen",
      "noResults": "Keine Ergebnisse gfundn"
    },
    "review": {
      "title": "Prüf-Warteschlange",
      "subtitle": "Eingereichte Ergebnisse prüfn",
      "submittedBy": "Eingereicht vo",
      "submittedAt": "Eingereicht am",
      "firstApproval": "Erste Freigabe",
      "awaitingSecond": "Wart auf zweite Freigabe",
      "noItems": "Keine Ergebnisse zum Prüfn",
      "reviewDetail": "Ergebnis prüfn",
      "approvalHistory": "Freigabe-Verlauf"
    },
    "status": {
      "draft": "Entwurf",
      "pendingReview": "Warten auf Prüfung",
      "published": "Veröffentlicht",
      "protestFiled": "Protest eingereicht",
      "invalid": "Ungültig"
    },
    "actions": {
      "edit": "Bearbeitn",
      "view": "O'zoagn",
      "submit": "Einreichn",
      "approve": "Freigem",
      "reject": "Ablehna",
      "protest": "Protest",
      "invalidate": "Ungültig macha",
      "saveDraft": "Entwurf speichan",
      "cancel": "Obbrechn",
      "confirm": "Bestätign",
      "back": "Zruck"
    },
    "form": {
      "newResult": "Neues Ergebnis erstölln",
      "editResult": "Ergebnis bearbeitn",
      "selectSport": "Sportoat auswähln",
      "selectEvent": "Wettbewerb auswähln",
      "selectAthlete": "Athlet auswähln",
      "enterValue": "Ergebniswert eigem",
      "enterUnit": "Einheit eigem",
      "enterRank": "Plotz",
      "notes": "Notizen",
      "sportSpecific": "Sportspezifische Felder",
      "reviewAndSave": "Prüfn & Speichan",
      "autoSaved": "Automatisch gspeichert",
      "required": "Pflichtfeld",
      "step": "Schritt",
      "of": "vo"
    },
    "modal": {
      "confirmSubmit": "Ergebnis einreichn?",
      "confirmSubmitMessage": "Des Ergebnis wird zur Prüfung eingereicht und ko danach nimma bearbeitet wern.",
      "confirmApprove": "Ergebnis freigem?",
      "confirmApproveMessage": "Wüst du des Ergebnis freigem?",
      "confirmReject": "Ergebnis ablehnna?",
      "confirmRejectMessage": "Bitte gib an Grund für de Ablehnung o.",
      "protestTitle": "Protest einreichn",
      "protestMessage": "Bitte gib an Grund für dein Protest o (max. 1000 Zeichn).",
      "invalidateTitle": "Ergebnis ungültig macha",
      "invalidateMessage": "Bitte gib an Grund für de Ungültigmachung o.",
      "reasonPlaceholder": "Grund eigem...",
      "rejectionPlaceholder": "Ablehnungsgrund eigem..."
    },
    "detail": {
      "title": "Ergebnis-Detail",
      "resultInfo": "Ergebnis-Informationen",
      "versionHistory": "Versionsverlauf",
      "reviewerFeedback": "Prüfer-Feedback",
      "auditTrail": "Audit-Protokoll",
      "protestHistory": "Protest-Verlauf",
      "changedBy": "Geändert vo",
      "changedAt": "Geändert am",
      "changeType": "Art vo da Änderung"
    }
  },
  "admin": {
    "dashboard": {
      "title": "Admin-Dashboard",
      "subtitle": "Systemübersicht und Vawoitung",
      "totalUsers": "Benutza insgsamt",
      "activeJudges": "Aktive Kampfrichda",
      "pendingResults": "Wartende Ergebnisse",
      "openProtests": "Offene Proteste",
      "forcePublishAlert": "Zwangsveröffentlichungen in de letztn 24 Stund",
      "userManagement": "Benutzervawoitung",
      "resultManagement": "Ergebnisvawoitung",
      "templates": "Vorlagn",
      "auditLog": "Audit-Protokoll",
      "assets": "Medaljn-Assets"
    },
    "users": {
      "title": "Benutzervawoitung",
      "subtitle": "Systembenutza vawaltn",
      "createUser": "Benutza erstölln",
      "allRoles": "Alle",
      "username": "Benutzaname",
      "email": "E-Mail",
      "role": "Rolle",
      "temporaryPassword": "Temporäres Passwoat",
      "cancel": "Obbrechn",
      "create": "Erstölln",
      "backToUsers": "Zruck zu de Benutza",
      "active": "Aktiv",
      "locked": "Gsperrt",
      "editProfile": "Profil bearbeitn",
      "save": "Speichan",
      "saving": "Wird gspeichert...",
      "lock": "Konto sperrn",
      "unlock": "Konto entsperrn",
      "lockTitle": "Benutza sperrn?",
      "unlockTitle": "Benutza entsperrn?",
      "lockMessage": "Der Benutza ko si dann nimma o'möln.",
      "unlockMessage": "Der Benutza ko si dann wieda o'möln.",
      "accountInfo": "Konto-Informationen",
      "createdAt": "Erstöllt am",
      "lastLogin": "Letztes Login",
      "updatedAt": "Aktualisiert am",
      "notFound": "Benutza ned gfundn",
      "table": {
        "username": "Benutzaname",
        "email": "E-Mail",
        "role": "Rolle",
        "status": "Status",
        "lastLogin": "Letztes Login",
        "delegation": "Delegation",
        "actions": "Aktionen",
        "active": "Aktiv",
        "locked": "Gsperrt",
        "view": "O'zoagn",
        "lock": "Sperrn",
        "unlock": "Entsperrn"
      },
      "delegation": {
        "title": "Prüfer-Delegation",
        "active": "Aktive Delegation",
        "revoke": "Widerrufen",
        "expiresAt": "Läuft ab",
        "delegatedBy": "Delegiert vo",
        "noDelegation": "Keine aktive Prüfer-Delegation",
        "validUntil": "Gültig bis",
        "delegate": "Prüferrechte delegiern"
      }
    },
    "results": {
      "title": "Ergebnisvawoitung",
      "subtitle": "Alle Ergebnisse über alle Status",
      "all": "Alle",
      "draft": "Entwurf",
      "pending": "Wartend",
      "published": "Veröffentlicht",
      "invalid": "Ungültig",
      "protest": "Protest",
      "event": "Wettbewerb",
      "athlete": "Athlet",
      "sport": "Sportoat",
      "value": "Wert",
      "status": "Status",
      "version": "Version",
      "submittedBy": "Eingereicht vo",
      "actions": "Aktionen",
      "view": "O'zoagn",
      "noResults": "Keine Ergebnisse gfundn",
      "backToResults": "Zruck zu de Ergebnisse",
      "resultInfo": "Ergebnis-Informationen",
      "rank": "Plotz",
      "createdBy": "Erstöllt vo",
      "submittedAt": "Eingereicht am",
      "firstApproval": "1. Freigabe",
      "secondApproval": "2. Freigabe",
      "notes": "Notizen",
      "protests": "Proteste",
      "versionHistory": "Versionsverlauf",
      "adminActions": "Admin-Aktionen",
      "restore": "Ergebnis wieda herstölln",
      "forcePublish": "Zwangsveröffentlichung",
      "permanentDelete": "Endgültig löschn",
      "restoreTitle": "Ergebnis wieda herstölln?",
      "restoreMessage": "Des stellt des Ergebnis auf Status Veröffentlicht wieda her.",
      "restoreReason": "Grund für de Wiederherstellung",
      "forcePublishTitle": "Zwangsveröffentlichung?",
      "forcePublishMessage": "Des umgeht den normalen Prüfprozess. Die Aktion wird protokolliert.",
      "forcePublishReason": "Grund für Zwangsveröffentlichung (mind. 20 Zeichn)",
      "deleteTitle": "Endgültig löschn?",
      "deleteMessage": "Des LÖSCHT des Ergebnis und alle zugehörigen Daten ENDGÜLTIG. Des ko ned rückgängig gmacht wern.",
      "deleteReason": "Grund fürs Löschn",
      "notFound": "Ergebnis ned gfundn"
    },
    "templates": {
      "title": "Sportvorlagn",
      "subtitle": "Ergebniseingabe-Vorlagn pro Sportoat vawaltn",
      "createTemplate": "Vorlag erstölln",
      "sport": "Sportoat",
      "fields": "Felder",
      "version": "Version",
      "status": "Status",
      "lastUpdated": "Zuletzt aktualisiert",
      "actions": "Aktionen",
      "active": "Aktiv",
      "inactive": "Inaktiv",
      "fieldCount": "Felder",
      "edit": "Bearbeitn",
      "noTemplates": "Keine Vorlagn gfundn",
      "sportId": "Sport-ID",
      "fieldsJson": "Felder (JSON)",
      "cancel": "Obbrechn",
      "create": "Erstölln",
      "backToTemplates": "Zruck zu de Vorlagn",
      "save": "Vorlag speichan",
      "saving": "Wird gspeichert...",
      "editFields": "Felder bearbeitn",
      "preview": "Vorschau",
      "noFields": "Keine Felder definiert",
      "notFound": "Vorlag ned gfundn",
      "editor": {
        "field": "Feld",
        "fieldName": "Feldname",
        "fieldType": "Typ",
        "unit": "Einheit",
        "required": "Pflichtfeld",
        "labels": "Bezeichnungen (pro Sproch)",
        "options": "Optionen (kommagetrennt)",
        "addField": "Feld hinzufügen"
      }
    },
    "audit": {
      "title": "Audit-Protokoll",
      "subtitle": "Vollständiger System-Audit-Trail",
      "exportCsv": "CSV exportiern",
      "filterUser": "Benutza",
      "filterUserPlaceholder": "Benutzaname",
      "filterAction": "Aktion",
      "filterActionPlaceholder": "z.B. FORCE_PUBLISH",
      "from": "Vo",
      "to": "Bis",
      "noEntries": "Keine Audit-Log Einträge gfundn",
      "table": {
        "timestamp": "Zeitstempel",
        "user": "Benutza",
        "action": "Aktion",
        "entity": "Entität",
        "entityId": "Entitäts-ID",
        "ip": "IP",
        "oldValue": "Alter Wert",
        "newValue": "Neuer Wert",
        "details": "Details"
      }
    },
    "assets": {
      "title": "Medaljn-Assets",
      "subtitle": "Medaljn-SVG-Assets vawaltn",
      "medal": "Medalj",
      "uploaded": "Hochgladen",
      "missing": "Fehlt",
      "backupAvailable": "Backup verfügbar",
      "lastModified": "Zuletzt geändert",
      "replace": "SVG ersetzen",
      "uploading": "Wird hochgladen..."
    },
    "modal": {
      "confirmPhrase": "Gib den Bestätigungstext ei, um fortzufoahrn",
      "reason": "Grund",
      "cancel": "Obbrechn",
      "confirm": "Bestätign"
    }
  },
  "sidebar": {
    "results": "Ergebnisse",
    "medalTable": "Medaillenspiagl",
    "sports": "Sportoatn",
    "myDashboard": "Mei Dashboard",
    "myResults": "Meine Ergebnisse",
    "newResult": "Neues Ergebnis",
    "reviewQueue": "Prüf-Warteschlange",
    "adminDashboard": "Admin-Dashboard",
    "userManagement": "Benutzervawoitung",
    "resultManagement": "Ergebnisvawoitung",
    "sportTemplates": "Sportvorlagn",
    "auditLog": "Audit-Protokoll",
    "medalAssets": "Medaljn-Assets",
    "login": "O'mölon",
    "logout": "O'bmeldn"
  }
}
